{"cameraMode":{"drawMode":0,"name":"Shaded","section":"Shading Mode"},"sceneLighting":true,"audioPlay":false,"sceneViewState":{"showFog":true,"showMaterialUpdate":false,"showSkybox":true,"showFlares":true,"showImageEffects":true,"showParticleSystems":true,"showVisualEffectGraphs":true,"m_FxEnabled":true},"in2DMode":false,"pivot":{"x":4.449470520019531,"y":4.324225902557373,"z":-5.185711860656738},"rotation":{"x":0.07232329994440079,"y":-0.7002605199813843,"z":0.0716753825545311,"w":0.7065912485122681},"size":14.957566261291504,"orthographic":true}